dj_storage/__init__.py
dj_storage/http.py
dj_storage/auth/__init__.py
dj_storage/auth/gcp.py
dj_storage-0.2.0.dist-info/LICENSE
dj_storage-0.2.0.dist-info/METADATA
dj_storage-0.2.0.dist-info/WHEEL
dj_storage-0.2.0.dist-info/top_level.txt
dj_storage-0.2.0.dist-info/zip-safe
dj_storage-0.2.0.dist-info/RECORD
