Metadata-Version: 2.1
Name: dj-storage
Version: 0.2.0
Summary: Nice file storage support for Django
Home-page: https://gitlab.com/aiakos/dj-storage
Author: Aiakos Contributors
Author-email: aiakos@aiakosauth.com
License: UNKNOWN
Keywords: google storage
Platform: UNKNOWN
Classifier: Development Status :: 4 - Beta
Classifier: Intended Audience :: Developers
Classifier: License :: OSI Approved :: MIT License
Classifier: Programming Language :: Python :: 3
Classifier: Programming Language :: Python :: 3 :: Only
Classifier: Programming Language :: Python :: 3.4
Classifier: Programming Language :: Python :: 3.5
Classifier: Programming Language :: Python :: 3.6
Classifier: Programming Language :: Python :: 3.7
Classifier: Framework :: Django
Classifier: Framework :: Django :: 2.0
Classifier: Framework :: Django :: 2.1
Requires-Dist: django (>=2.0.0)
Provides-Extra: gcp
Requires-Dist: google-auth ; extra == 'gcp'
